README.md
setup.py
groupdocs_classification_cloud.egg-info/PKG-INFO
groupdocs_classification_cloud.egg-info/SOURCES.txt
groupdocs_classification_cloud.egg-info/dependency_links.txt
groupdocs_classification_cloud.egg-info/requires.txt
groupdocs_classification_cloud.egg-info/top_level.txt
groupdocsclassificationcloud/__init__.py
groupdocsclassificationcloud/api_client.py
groupdocsclassificationcloud/configuration.py
groupdocsclassificationcloud/rest.py
groupdocsclassificationcloud/apis/__init__.py
groupdocsclassificationcloud/apis/classification_api.py
groupdocsclassificationcloud/models/__init__.py
groupdocsclassificationcloud/models/base_request.py
groupdocsclassificationcloud/models/base_response.py
groupdocsclassificationcloud/models/classification_response.py
groupdocsclassificationcloud/models/classification_result.py
groupdocsclassificationcloud/models/classify_request.py
groupdocsclassificationcloud/models/file_info.py
groupdocsclassificationcloud/models/format.py
groupdocsclassificationcloud/models/format_collection.py
groupdocsclassificationcloud/models/get_supported_file_formats_request.py
test/__init__.py
test/base_test_context.py
test/test_classify.py
test/test_get_supported_file_formats.py
test/Common/__init__.py
test/Common/test_api_coverage.py
test/Common/test_error_handling.py