Metadata-Version: 1.1
Name: groupdocs-classification-cloud
Version: 19.3.0
Summary: GroupDocs.Classification Cloud API References
Home-page: https://github.com/groupdocs-classification-cloud/groupdocs-classification-cloud-python
Author: GroupDocs Classification
Author-email: UNKNOWN
License: UNKNOWN
Download-URL: https://github.com/groupdocs-classification-cloud/groupdocs-classification-cloud-python/archive/19.3.0.tar.gz
Keywords: groupdocs,python,groupdocs cloud,classification,documents classification,iab2,taxonomy
Platform: UNKNOWN
Classifier: Development Status :: 5 - Production/Stable
Classifier: Intended Audience :: Developers
Classifier: Topic :: Office/Business :: Office Suites
Classifier: Topic :: Software Development :: Libraries
Classifier: License :: OSI Approved :: MIT License
Classifier: Programming Language :: Python :: 2.7
Classifier: Programming Language :: Python :: 3.4
Classifier: Programming Language :: Python :: 3.5
Classifier: Programming Language :: Python :: 3.6
